pandas_extension_christine/__init__.py
pandas_extension_christine/christine.py
pandas_extension_christinedonszelmann-0.2.3.dist-info/METADATA
pandas_extension_christinedonszelmann-0.2.3.dist-info/WHEEL
pandas_extension_christinedonszelmann-0.2.3.dist-info/top_level.txt
pandas_extension_christinedonszelmann-0.2.3.dist-info/RECORD
