Metadata-Version: 2.1
Name: pandas-extension-christinedonszelmann
Version: 0.2.3
Summary: makes combinations of all columns of one dataframe, and more
Home-page: UNKNOWN
Author: Christine Donszelmann
Author-email: christine.donszelmann@nl.ey.com
License: MIT
Platform: UNKNOWN
